apistubs/__init__.py
apistubs/apps.py
apistubs/constants.py
apistubs/helpers.py
apistubs/logging.py
apistubs/middleware.py
apistubs/models.py
apistubs/spec.py
apistubs/stubs.py
apistubs/urls.py
apistubs/dbpreset/__init__.py
apistubs/dbpreset/apps.py
apistubs/dbpreset/models.py
apistubs/dbpreset/migrations/0001_initial.py
apistubs/dbpreset/migrations/0002_auto_20240630_1641.py
apistubs/dbpreset/migrations/__init__.py
apistubs/openapi/__init__.py
apistubs/openapi/middleware.py
apistubs/openapi/stubforce.py
apistubs/tests/__init__.py
apistubs/tests/test_helpers.py
apistubs/tests/test_views_common.py
apistubs/tests/test_views_prompt.py
apistubs/tests/test_views_settings.py
apistubs/tests/test_views_specification.py
apistubs/views/__init__.py
apistubs/views/common.py
apistubs/views/logging.py
apistubs/views/prompt.py
apistubs/views/settings.py
apistubs/views/stub.py
apistubs-0.0.1.dist-info/licenses/LICENSE
apistubs-0.0.1.dist-info/METADATA
apistubs-0.0.1.dist-info/WHEEL
apistubs-0.0.1.dist-info/top_level.txt
apistubs-0.0.1.dist-info/RECORD
