Metadata-Version: 2.4
Name: apistubs
Version: 0.0.1
Summary: APISTUBS: Active stubs service, which can interact with tests generator and LLMs
Author-email: Eugene Rabtsau <e.ryabtsev@gmail.com>
Project-URL: Source, https://github.com/ryabtsev/apistubs
Classifier: Programming Language :: Python :: 3
Classifier: License :: OSI Approved :: BSD License
Classifier: Operating System :: OS Independent
Requires-Python: >=3.8
License-File: LICENSE
Requires-Dist: requests
Requires-Dist: PyYAML
Requires-Dist: Jinja2
Requires-Dist: parse
Requires-Dist: mock
Requires-Dist: Django
Requires-Dist: openapi-core
Requires-Dist: uvicorn
Requires-Dist: fastapi
Dynamic: license-file
